plansi/__init__.py
plansi/__main__.py
plansi/player.py
plansi/core/__init__.py
plansi/core/terminal_render.py
plansi/core/video.py
plansi-0.0.4.dist-info/entry_points.txt
plansi-0.0.4.dist-info/licenses/LICENSE.md
plansi-0.0.4.dist-info/WHEEL
plansi-0.0.4.dist-info/METADATA
plansi-0.0.4.dist-info/RECORD
