Metadata-Version: 2.4
Name: plansi
Version: 0.0.4
Summary: plays videos as ansi
Author-email: Gareth Davidson <gaz@bitplane.net>
Requires-Python: >=3.10
License-File: LICENSE.md
Requires-Dist: bittty==0.0.6
Requires-Dist: chafa.py~=1.2
Requires-Dist: av~=15.0
Requires-Dist: Pillow~=11.3
Requires-Dist: pre-commit ; extra == "dev"
Requires-Dist: pytest ; extra == "dev"
Requires-Dist: coverage ; extra == "dev"
Requires-Dist: pytest-cov ; extra == "dev"
Requires-Dist: build ; extra == "dev"
Requires-Dist: twine ; extra == "dev"
Requires-Dist: ruff ; extra == "dev"
Requires-Dist: pydoc-markdown ; extra == "dev"
Provides-Extra: dev
